autoasm/__init__.py
autoasm/config.py
autoasm/core.py
autoasm/execptions.py
tests/__init__.py
tests/test_injector.py
autoasm-0.1.4.dist-info/LICENSE
autoasm-0.1.4.dist-info/METADATA
autoasm-0.1.4.dist-info/WHEEL
autoasm-0.1.4.dist-info/top_level.txt
autoasm-0.1.4.dist-info/RECORD
