Metadata-Version: 2.1
Name: autoasm
Version: 0.1.4
Summary: simple dependency inject
Home-page: https://github.com/neoblackcap/conveyor
Author: neo
Author-email: neo.blackcap@gmail.com
License: Apache 2.0 License
Keywords: dependency inject
Platform: UNKNOWN
Classifier: Programming Language :: Python :: 3
Classifier: Programming Language :: Python :: 3.6
